modulos/ControlUnit.sv
module ControlUnit(
	input logic [6:0] opcode,
	input logic [2:0] funct3,
	input logic [6:0] funct7,
	output logic [3:0] ALUOp,
	output logic [2:0] ImmSrc,
	output logic [4:0] BrOp,
	output logic [2:0] DMCtrl,
	output logic [1:0] RUDataWrSrc,
	output logic RuWr,
	output logic DMWr,
	output logic AluASrc,
	output logic AluBSrc
);

parameter R = 7'b0110011;
parameter I = 7'b0010011;
parameter L = 7'b0000011;
parameter S = 7'b0100011;
parameter B = 7'b1100011;
parameter LUI = 7'b0110111;
parameter AUIPC = 7'b0010111;
parameter J = 7'b1101111;
parameter JR = 7'b1100111;



always@(*)
	case (opcode)
		R: begin
				RuWr = 1'b1;
				ImmSrc = 3'bxxx;
				BrOp = 5'b00xxx;
				ALUOp = {funct7[5], funct3};
				DMCtrl = 3'bxxx;
				DMWr = 1'b0;
				RUDataWrSrc = 2'b00;
				AluASrc = 1'b0;
				AluBSrc = 1'b0;
			end
		I:	begin
				RuWr = 1'b1;
				ImmSrc = 3'b000;
				BrOp = 5'b00xxx;
				if(funct3 == 3'b000)
					ALUOp <= {funct7[5], funct3};
				else
					ALUOp <= {1'b0, funct3};
				DMCtrl = 3'bxxx;
				DMWr = 1'b0;
				RUDataWrSrc = 2'b00;
				AluASrc = 1'b0;
				AluBSrc = 1'b1;
			end
		L:	begin
				RuWr = 1'b1;
				ImmSrc = 3'b000;
				BrOp = 5'b00xxx;
				ALUOp = 4'b0000;
				DMCtrl = funct3;
				DMWr = 1'b0;
				RUDataWrSrc = 2'b01;
				AluASrc = 1'b0;
				AluBSrc = 1'b1;
			end
		S: 	begin
				RuWr = 1'b0;
				ImmSrc = 3'b001;
				BrOp = 5'b00xxx;
				ALUOp = 4'b0000;
				DMCtrl = funct3;
				DMWr = 1'b1;
				RUDataWrSrc = 2'b01;
				AluASrc = 1'b0;
				AluBSrc = 1'b1;
			end
			

		B:	begin
				RuWr = 1'b0;
				ImmSrc = 3'b101;
				BrOp = { 2'b01, funct3 };
				ALUOp = 4'b0000;
				DMCtrl = 3'bxxx;
				DMWr = 1'b0;
				RUDataWrSrc = 2'bxx;
				AluASrc = 1'b1;
				AluBSrc = 1'b1;
			end
		LUI: begin
			RuWr = 1'b1;
			ImmSrc = 3'b010;
			BrOp = 5'b00xxx;
			ALUOp = 4'b1111;
			DMCtrl = 3'bxxx;
			DMWr = 1'b0;
			RUDataWrSrc = 2'b00;
			AluASrc = 1'bx;
			AluBSrc = 1'b1;
		end

		AUIPC:
			begin
				RuWr = 1'b1;
				ImmSrc = 3'b010;
				BrOp = 5'b00xxx;
				ALUOp = 4'b0000;
				DMCtrl = 3'bxxx;
				DMWr = 1'b0;
				RUDataWrSrc = 2'b00;
				AluASrc = 1'b1;
				AluBSrc = 1'b1;
			end

		J:	begin
				RuWr = 1'b1;
				ImmSrc = 3'b110;
				BrOp = 5'b1xxxx;
				ALUOp = 4'b0000;
				DMCtrl = 3'bxxx;
				DMWr = 1'b0;
				RUDataWrSrc = 2'b10;
				AluASrc = 1'b1;
				AluBSrc = 1'b1;
			end

		JR:	begin
				RuWr = 1'b1;
				ImmSrc = 3'b000;
				BrOp = 5'b1xxxx;
				ALUOp = 4'b0000;
				DMCtrl = 3'bxxx;
				DMWr = 1'b0;
				RUDataWrSrc = 2'b10;
				AluASrc = 1'b1;
				AluBSrc = 1'b1;
			end

		default: begin
				RuWr = 1'b0;
				ImmSrc = 3'bxxx;
				BrOp = 5'b00xxx;
				ALUOp = 4'bxxxx;
				DMCtrl = 3'bxxx;
				DMWr = 1'b0;
				RUDataWrSrc = 2'bxx;
				AluASrc = 1'bx;
				AluBSrc = 1'bx;
			end
	endcase
endmodule

BranchUnit.sv
module branchunit(A,B,BrOp,NextPCSrc);
    input logic [31:0] A, B; //Bus de datos de 32 bits
    input logic [4:0] BrOp; //Bus de control de 4 bits
    output logic  NextPCSrc; //Bus de salida de 2 bits

    always @* begin
        if (BrOp[4] == 1'b1)
            NextPCSrc = 1;
        else if (BrOp[3] == 1'b0)
            NextPCSrc = 0;
        else if (BrOp == 5'b01000) begin
            if (A == B)
                NextPCSrc = 1;
            else
                NextPCSrc = 0;
        end
        else if (BrOp == 5'b01001) begin
            if (A != B)
                NextPCSrc = 1;
            else
                NextPCSrc = 0;
        end
        else if (BrOp == 5'b01100) begin
            if (A < B)
                NextPCSrc = 1;
            else
                NextPCSrc = 0;
        end
        else if (BrOp == 5'b01101) begin
            if (A >= B)
                NextPCSrc = 1;
            else
                NextPCSrc = 0;
        end
        else if (BrOp == 5'b01110) begin
            if ($unsigned(A) < $unsigned(B))
                NextPCSrc = 1;
            else
                NextPCSrc = 0;
        end
        else if (BrOp == 5'b01111) begin
            if ($unsigned(A) >= $unsigned(B))
                NextPCSrc = 1;
            else
                NextPCSrc = 0;
        end
    end
    
endmodule

modulos/DataMemory.sv
module DataMemory(Address, DataWr, DMWr, DMCtrl, DataRd);
    input logic [31:0] Address, DataWr; //Bus de datos de 32 bits
    input logic DMWr; //Habilitador de escritura
    input logic [2:0] DMCtrl; //Bus de control de 2 bits
    output logic [31:0] DataRd; //Bus de salida de 32 bits
    logic [7:0] memoria [1023:0]; //Memoria de 1024 posiciones de 8 bits
    //inicializa la memoria en cero
    initial begin
        for (int i = 0; i < 1024; i = i + 1) begin
            memoria[i] = 8'b0;
        end
    end
    
    always @* begin
        // en 1 escribe en memoria
        if (DMWr == 1) begin
            case (DMCtrl)
                3'b000: begin // B 8 bits
                    memoria[Address] <= DataWr[7:0];
                end
                3'b001: begin // H 16 bits
                    memoria[Address] <= DataWr[15:8];
                    memoria[Address + 1] <= DataWr[7:0];
                end
                3'b010: begin // W 32 bits
                    memoria[Address] <= DataWr[31:24];
                    memoria[Address + 1] <= DataWr[23:16];
                    memoria[Address + 2] <= DataWr[15:8];
                    memoria[Address + 3] <= DataWr[7:0];
                end
                3'b100: begin // B(u)
                    memoria[Address] <= DataWr[7:0];
                end
                3'b101: begin // H(u)
                    memoria[Address] <= DataWr[15:8];
                    memoria[Address + 1] <= DataWr[7:0];
                end
            endcase
        end
        // en 0 lee de memoria
        else begin
            case (DMCtrl)
                3'b000: begin // B 8 bits
                    DataRd <= {{24{memoria[Address][7]}}, memoria[Address]};
                end
                3'b001: begin // H 16 bits
                    DataRd <= {{16{memoria[Address][7]}}, memoria[Address], memoria[Address + 1]};
                end
                3'b010: begin // W 32 bits
                    DataRd <= {memoria[Address], memoria[Address + 1], memoria[Address + 2], memoria[Address + 3]};
                end
                3'b100: begin // B(u)
                    DataRd <= {{24'b0}, memoria[Address]};
                end
                3'b101: begin // H(u)
                    DataRd <= {{16'b0}, memoria[Address + 1], memoria[Address]};
                end
                default: begin
                    DataRd <= 32'b0;
                end
            endcase
        end
    end
endmodule

modulos/Alu.sv
//ALU
//Desing
module ALU (A,B,ALUop,ALUS);
  input logic [31:0] A, B; //Bus de datos de 32 bits
  input logic [3:0] ALUop; //Bus de control de 4 bits
  output logic signed [31:0] ALUS; //Bus de salida de 32 bits
  
  always @*
    begin 
      case (ALUop)
        4'b0000: ALUS = A + B; //0 suma
        4'b1000: ALUS = A - B; //1 resta
        4'b0001: ALUS = A << B; //2 shift left
        4'b0010: ALUS = A < B; //3 signed
        4'b0011: ALUS = $unsigned(A) < $unsigned(B); //4(unsigned)
        4'b0100: ALUS = A ^ B; //5 xor
        4'b0101: ALUS = A >> B; //6 shift right
        // B tiene que ser menor que 32
        4'b1101: ALUS = A >>> B[4:0]; //7 
        4'b0110: ALUS = A | B; //8 or
        4'b0111: ALUS = A & B; //9 and
        default: ALUS = 4'b0; // Manejar caso no definido
      endcase
    end

endmodule

modulos/ImmGen.sv
module ImmGen(Inst, ImmScr, ImmExt);
    input logic[24:0] Inst;
    input logic[2:0] ImmScr;
    output logic[31:0] ImmExt;
    
    // I 000 S 001 B 101 U 010 J 110
    always @* begin //cambia con cualquier cambio en las entradas
        case(ImmScr)
            3'b000: ImmExt = {{20{Inst[24]}}, Inst[24:13]}; // Rango completo de ImmExt
            3'b001: ImmExt = {{9{Inst[24]}}, Inst[24:18], Inst[4:0]}; // Rango completo de ImmExt
            3'b101: ImmExt = {{9{Inst[24]}}, Inst[0], Inst[23:18], Inst[4:1], 1'b0}; // Rango completo de ImmExt
            3'b010: ImmExt = {Inst[24:5],12'b0}; // Rango completo de ImmExt
            3'b110: ImmExt = {Inst[24], Inst[12:5], Inst[13], Inst[23:14],1'b0}; // Rango completo de ImmExt
            default: ImmExt = 32'b0;
        endcase
    end
endmodule

modulos/Registerunit.sv
module registerUnit (
  input logic [31:0] RuDataWrite, //datos a escribir
  input logic [4:0] rd,  			//donde escribir
  input logic [4:0] rs1,			//que registro leer
  input logic [4:0] rs2,			//que registro leer
  input logic clk,					//reloj
  input logic Ruwr,					//habilitador de escritura
  output logic [31:0] Ru1,				//salida de registro que se lee
  output logic [31:0] Ru2				//salida de registro que se lee
);

  logic [31:0] reg_file [31:0];		//vector que contiene los registros
  initial begin
    for (int i = 0; i < 32; i++) begin
      reg_file[i] = 32'h00000000;
    end
  end
  always_ff @(negedge clk) begin
    //el registro en la posicion 0 siempre es 0
    if (Ruwr && rd != 5'b00000) reg_file[rd] <= RuDataWrite;
  end

  always @* begin
    Ru1 = reg_file[rs1];
    Ru2 = reg_file[rs2];
  end

endmodule

InstructionMemory.sv
module InstructionMemory(
    input logic [31:0] Adress,
    output logic [31:0] Inst
);
    /*
     Defino una matriz llamada mem que contiene los datos de la memoria de instrucciones., 
     cada uno de los cuales es un byte (8 bits) de datos. Esta matriz es
     para tiene que ser de un tamaño en el que quepan todas las instrucciones si no salta un warning
    */
    logic [7:0] mem [0:1023];
    // Leo mi archivo memfile
    initial begin
        $readmemh("memfile2.mem",mem); 
    end
    always @* begin
        Inst = {mem[Adress],mem[Adress + 1],mem[Adress + 2],mem[Adress + 3]};
    end

endmodule

modulos/PcCounter.sv
module PcCounter(
    input logic clk,
    input logic [31:0] pc,
    output logic [31:0] pc_out
);
    initial begin
        pc_out = 32'h0;
    end
    always_ff @(posedge clk) begin
        pc_out <= pc;
    end
endmodule

monociclo.sv
module monociclo;
    logic [31:0] pc; //entrada de pc counter
    logic [31:0] pc_out; //salida de pc counter
    logic [31:0] inst; //salida de instruction memory
    logic [31:0] ru1, ru2; //salida de register unit 
    logic [31:0] A,B ; //entrada alu
    logic [31:0] ImmExt; //salida de ImmGen
    logic [31:0] alu_out; //salida de alu
    logic [31:0] DataRd; //salida de DataMemory
    logic NextPCSrc; //salida de branch unit
    logic [31:0] muxData; //entrada de DataWrite en la register unit 
    logic [31:0] pc4; //pc + 4
    //señales de control y salidas de control unit
    logic AluASrc,AluBSrc,RuWr,DMWr;
    logic [1:0] RUDataWrSrc;
    logic [2:0] ImmSrc,DMCtrl;
    logic [3:0] AluOP;
    logic [4:0] BrOp;

    logic clk = 0; 
    // Generación de clock
    always #15 clk = ~clk;

    // Inicialización de señales
    initial begin
        $dumpfile("monociclo.vcd");
        $dumpvars(0, monociclo);
        pc = 32'h0;
        #900; // tiempo que se demora en recorrer todas las instrucciones
        $finish;
        // Otros valores de señales de entrada necesarios para la simulación
    end

    //instancias de los modulos
    PcCounter pc_counter(
        .clk(clk),
        .pc(pc),
        .pc_out(pc_out)
    );
    InstructionMemory inst_mem(
        .Adress(pc_out),
        .Inst(inst)
    );
    registerUnit ru(
        .RuDataWrite(muxData),
        .rd(inst[11:7]),
        .rs1(inst[19:15]),
        .rs2(inst[24:20]),
        .clk(clk),
        .Ruwr(RuWr),
        .Ru1(ru1),
        .Ru2(ru2)
    );
    ImmGen imm_gen(
        .Inst(inst[31:7]),
        .ImmScr(ImmSrc),
        .ImmExt(ImmExt)
    );
    ALU alu1(
        .A(A),
        .B(B),
        .ALUop(AluOP),
        .ALUS(alu_out)
    );
    DataMemory data_mem(
        .Address(alu_out),
        .DataWr(ru2),
        .DMWr(DMWr),
        .DMCtrl(DMCtrl),
        .DataRd(DataRd)
    );
    branchunit branch_unit(
        .A(ru1),
        .B(ru2),
        .BrOp(BrOp),
        .NextPCSrc(NextPCSrc)
    );
    ControlUnit control_unit(
        .opcode(inst[6:0]),
        .funct3(inst[14:12]),
        .funct7(inst[31:25]),
        .AluASrc(AluASrc),
        .AluBSrc(AluBSrc),
        .RuWr(RuWr),
        .ImmSrc(ImmSrc),
        .ALUOp(AluOP),
        .BrOp(BrOp),
        .DMWr(DMWr),
        .DMCtrl(DMCtrl),
        .RUDataWrSrc(RUDataWrSrc)
    );
    

    always @* begin
        pc4 = pc_out + 32'h4;
        case(AluASrc)
            1'b0: A = ru1;
            1'b1: A = pc_out;
        endcase
        case(AluBSrc)
            1'b0: B = ru2;
            1'b1: B = ImmExt;
        endcase
        case(NextPCSrc)
            1'b0: pc = pc4;
            1'b1: pc = alu_out;
        endcase
        case(RUDataWrSrc)
            2'b10: muxData = pc4;
            2'b01: muxData = DataRd;
            2'b00: muxData = alu_out;
        endcase   
    end

     
    
endmodule

monociclo.vcd
$date
	Mon Apr 29 12:19:51 2024
$end
$version
	Icarus Verilog
$end
$timescale
	1s
$end
$scope module monociclo $end
$var wire 32 ! ru2 [31:0] $end
$var wire 32 " ru1 [31:0] $end
$var wire 32 # pc_out [31:0] $end
$var wire 32 $ inst [31:0] $end
$var wire 32 % alu_out [31:0] $end
$var wire 1 & RuWr $end
$var wire 2 ' RUDataWrSrc [1:0] $end
$var wire 1 ( NextPCSrc $end
$var wire 3 ) ImmSrc [2:0] $end
$var wire 32 * ImmExt [31:0] $end
$var wire 32 + DataRd [31:0] $end
$var wire 1 , DMWr $end
$var wire 3 - DMCtrl [2:0] $end
$var wire 5 . BrOp [4:0] $end
$var wire 4 / AluOP [3:0] $end
$var wire 1 0 AluBSrc $end
$var wire 1 1 AluASrc $end
$var reg 32 2 A [31:0] $end
$var reg 32 3 B [31:0] $end
$var reg 1 4 clk $end
$var reg 32 5 muxData [31:0] $end
$var reg 32 6 pc [31:0] $end
$var reg 32 7 pc4 [31:0] $end
$scope module alu1 $end
$var wire 32 8 A [31:0] $end
$var wire 32 9 B [31:0] $end
$var wire 4 : ALUop [3:0] $end
$var reg 32 ; ALUS [31:0] $end
$upscope $end
$scope module branch_unit $end
$var wire 5 < BrOp [4:0] $end
$var wire 32 = B [31:0] $end
$var wire 32 > A [31:0] $end
$var reg 1 ( NextPCSrc $end
$upscope $end
$scope module control_unit $end
$var wire 3 ? funct3 [2:0] $end
$var wire 7 @ funct7 [6:0] $end
$var wire 7 A opcode [6:0] $end
$var reg 4 B ALUOp [3:0] $end
$var reg 1 1 AluASrc $end
$var reg 1 0 AluBSrc $end
$var reg 5 C BrOp [4:0] $end
$var reg 3 D DMCtrl [2:0] $end
$var reg 1 , DMWr $end
$var reg 3 E ImmSrc [2:0] $end
$var reg 2 F RUDataWrSrc [1:0] $end
$var reg 1 & RuWr $end
$upscope $end
$scope module data_mem $end
$var wire 32 G Address [31:0] $end
$var wire 3 H DMCtrl [2:0] $end
$var wire 1 , DMWr $end
$var wire 32 I DataWr [31:0] $end
$var reg 32 J DataRd [31:0] $end
$scope begin $ivl_for_loop0 $end
$var integer 32 K i [31:0] $end
$upscope $end
$upscope $end
$scope module imm_gen $end
$var wire 3 L ImmScr [2:0] $end
$var wire 25 M Inst [24:0] $end
$var reg 32 N ImmExt [31:0] $end
$upscope $end
$scope module inst_mem $end
$var wire 32 O Adress [31:0] $end
$var reg 32 P Inst [31:0] $end
$upscope $end
$scope module pc_counter $end
$var wire 1 4 clk $end
$var wire 32 Q pc [31:0] $end
$var reg 32 R pc_out [31:0] $end
$upscope $end
$scope module ru $end
$var wire 32 S RuDataWrite [31:0] $end
$var wire 1 & Ruwr $end
$var wire 1 4 clk $end
$var wire 5 T rd [4:0] $end
$var wire 5 U rs1 [4:0] $end
$var wire 5 V rs2 [4:0] $end
$var reg 32 W Ru1 [31:0] $end
$var reg 32 X Ru2 [31:0] $end
$scope begin $ivl_for_loop1 $end
$var integer 32 Y i [31:0] $end
$upscope $end
$upscope $end
$upscope $end
$enddefinitions $end
$comment Show the parameter values. $end
$dumpall
$end
#0
$dumpvars
b100000 Y
b0 X
b0 W
b1100 V
b10 U
b10 T
b11111111111111111111111111101100 S
b0 R
b100 Q
b11111110110000010000000100010011 P
b0 O
b11111111111111111111111111101100 N
b1111111011000001000000010 M
b0 L
b10000000000 K
bx J
b0 I
b0 H
b11111111111111111111111111101100 G
b0 F
b0 E
b0 D
b0 C
b0 B
b10011 A
b1111111 @
b0 ?
b0 >
b0 =
b0 <
b11111111111111111111111111101100 ;
b0 :
b11111111111111111111111111101100 9
b0 8
b100 7
b100 6
b11111111111111111111111111101100 5
04
b11111111111111111111111111101100 3
b0 2
01
10
b0 /
b0 .
b0 -
0,
bx +
b11111111111111111111111111101100 *
b0 )
0(
b0 '
1&
b11111111111111111111111111101100 %
b11111110110000010000000100010011 $
b0 #
b0 "
b0 !
$end
#15
b11111111111111111111111111101100 5
b11111111111111111111111111101100 S
b0 3
b0 9
b10 -
b10 D
b10 H
1,
b1 )
b1 E
b1 L
0&
b0 *
b0 N
b11111111111111111111111111101100 %
b11111111111111111111111111101100 ;
b11111111111111111111111111101100 G
b0 @
b10 ?
b100011 A
b10000001001000000 M
b1000 V
b0 T
b1000 6
b1000 Q
b11111111111111111111111111101100 2
b11111111111111111111111111101100 8
b1000 7
b100000010010000000100011 $
b100000010010000000100011 P
b11111111111111111111111111101100 "
b11111111111111111111111111101100 >
b11111111111111111111111111101100 W
b100 #
b100 O
b100 R
14
#30
04
#45
b11111111111111111111111111110000 5
b11111111111111111111111111110000 S
b11111111111111111111111111110000 %
b11111111111111111111111111110000 ;
b11111111111111111111111111110000 G
b100 3
b100 9
b100 *
b100 N
b10010001001000100 M
b1001 V
b100 T
b1100 6
b1100 Q
b1100 7
b100100010010001000100011 $
b100100010010001000100011 P
b1000 #
b1000 O
b1000 R
14
#60
04
#75
b11111111111111111111111111110100 5
b11111111111111111111111111110100 S
b11111111111111111111111111110100 %
b11111111111111111111111111110100 ;
b11111111111111111111111111110100 G
b1000 3
b1000 9
b1000 *
b1000 N
b100100001001001000 M
b10010 V
b1000 T
b10000 6
b10000 Q
b10000 7
b1001000010010010000100011 $
b1001000010010010000100011 P
b1100 #
b1100 O
b1100 R
14
#90
04
#105
b11111111111111111111111111111000 5
b11111111111111111111111111111000 S
b11111111111111111111111111111000 %
b11111111111111111111111111111000 ;
b11111111111111111111111111111000 G
b1100 3
b1100 9
b1100 *
b1100 N
b100110001001001100 M
b10011 V
b1100 T
b10100 6
b10100 Q
b10100 7
b1001100010010011000100011 $
b1001100010010011000100011 P
b10000 #
b10000 O
b10000 R
14
#120
04
#135
b11111111111111111111111111111100 5
b11111111111111111111111111111100 S
b11111111111111111111111111111100 %
b11111111111111111111111111111100 ;
b11111111111111111111111111111100 G
b10000 3
b10000 9
b10000 *
b10000 N
b101000001001010000 M
b10100 V
b10000 T
b11000 6
b11000 Q
b11000 7
b1010000010010100000100011 $
b1010000010010100000100011 P
b10100 #
b10100 O
b10100 R
14
#150
04
#165
b0 +
b0 J
b0 5
b0 S
b0 %
b0 ;
b0 G
b0 3
b0 9
b0 2
b0 8
b0 -
b0 D
b0 H
0,
b0 )
b0 E
b0 L
1&
b0 *
b0 N
b0 "
b0 >
b0 W
b0 ?
b10011 A
b101000001000 M
b0 V
b1010 U
b1000 T
b11100 6
b11100 Q
b11100 7
b1010000010000010011 $
b1010000010000010011 P
b11000 #
b11000 O
b11000 R
14
#180
04
#195
b101100001001 M
b1011 U
b1001 T
b100000 6
b100000 Q
b100000 7
b1011000010010010011 $
b1011000010010010011 P
b11100 #
b11100 O
b11100 R
14
#210
04
#225
b10010 M
b0 U
b10010 T
b100100 6
b100100 Q
b100100 7
b100100010011 $
b100100010011 P
b100000 #
b100000 O
b100000 R
14
#240
04
#255
b10011 M
b10011 T
b101000 6
b101000 Q
b101000 7
b100110010011 $
b100110010011 P
b100100 #
b100100 O
b100100 R
14
#270
04
#285
b1100100 5
b1100100 S
b1100100 %
b1100100 ;
b1100100 G
1(
b111100 3
b111100 9
b101000 2
b101000 8
b1101 .
b1101 <
b1101 C
b101 )
b101 E
b101 L
0&
11
b111100 *
b111100 N
b1 @
b101 ?
b1100011 A
b1010011001110111100 M
b1001 V
b10011 U
b11100 T
b1100100 6
b1100100 Q
b101100 7
b10100110011101111001100011 $
b10100110011101111001100011 P
b101000 #
b101000 O
b101000 R
14
#300
04
#315
0(
b0 5
b0 S
b1101000 6
b1101000 Q
b0 3
b0 9
b0 .
b0 <
b0 C
b0 )
b0 E
b0 L
1&
01
b0 *
b0 N
b0 %
b0 ;
b0 G
b0 @
b0 ?
b10011 A
b100000001010 M
b0 V
b1000 U
b1010 T
b0 2
b0 8
b1101000 7
b1000000010100010011 $
b1000000010100010011 P
b1100100 #
b1100100 O
b1100100 R
14
#330
04
#345
bx 5
bx S
bx +
bx J
b11111111111111111111111111101100 %
b11111111111111111111111111101100 ;
b11111111111111111111111111101100 G
b11111111111111111111111111101100 2
b11111111111111111111111111101100 8
b1 '
b1 F
b10 -
b10 D
b10 H
b11111111111111111111111111101100 "
b11111111111111111111111111101100 >
b11111111111111111111111111101100 W
b10 ?
b11 A
b1001001000 M
b10 U
b1000 T
b1101100 6
b1101100 Q
b1101100 7
b10010010000000011 $
b10010010000000011 P
b1101000 #
b1101000 O
b1101000 R
14
#360
04
#375
b11111111111111111111111111110000 %
b11111111111111111111111111110000 ;
b11111111111111111111111111110000 G
b100 3
b100 9
b100 *
b100 N
b1000001001001001 M
b100 V
b1001 T
b1110000 6
b1110000 Q
b1110000 7
b10000010010010010000011 $
b10000010010010010000011 P
b1101100 #
b1101100 O
b1101100 R
14
#390
04
#405
b11111111111111111111111111110100 %
b11111111111111111111111111110100 ;
b11111111111111111111111111110100 G
b1000 3
b1000 9
b1000 *
b1000 N
bx !
bx =
bx I
bx X
b10000001001010010 M
b1000 V
b10010 T
b1110100 6
b1110100 Q
b1110100 7
b100000010010100100000011 $
b100000010010100100000011 P
b1110000 #
b1110000 O
b1110000 R
14
#420
04
#435
b11111111111111111111111111111000 %
b11111111111111111111111111111000 ;
b11111111111111111111111111111000 G
b1100 3
b1100 9
b1100 *
b1100 N
b0 !
b0 =
b0 I
b0 X
b11000001001010011 M
b1100 V
b10011 T
b1111000 6
b1111000 Q
b1111000 7
b110000010010100110000011 $
b110000010010100110000011 P
b1110100 #
b1110100 O
b1110100 R
14
#450
04
#465
b11111111111111111111111111111100 %
b11111111111111111111111111111100 ;
b11111111111111111111111111111100 G
b10000 3
b10000 9
b10000 *
b10000 N
b100000001001010100 M
b10000 V
b10100 T
b1111100 6
b1111100 Q
b1111100 7
b1000000010010101000000011 $
b1000000010010101000000011 P
b1111000 #
b1111000 O
b1111000 R
14
#480
04
#495
b0 +
b0 J
b0 %
b0 ;
b0 G
b0 5
b0 S
b10100 3
b10100 9
b0 '
b0 F
b0 -
b0 D
b0 H
b10100 *
b10100 N
bx !
bx =
bx I
bx X
b0 ?
b10011 A
b101000001000000010 M
b10100 V
b10 T
b10000000 6
b10000000 Q
b10000000 7
b1010000010000000100010011 $
b1010000010000000100010011 P
b1111100 #
b1111100 O
b1111100 R
14
#510
04
#525
bx +
bx J
b10000100 5
b10000100 S
b1000000000000000 3
b1000000000000000 9
1(
b1000000010000000 %
b1000000010000000 ;
b1000000010000000 G
b10 '
b10 F
b10000 .
b10000 <
b10000 C
b110 )
b110 E
b110 L
11
b1000000000000000 *
b1000000000000000 N
b0 !
b0 =
b0 I
b0 X
b10000000 2
b10000000 8
b1100111 A
b100000000 M
b0 V
b1 U
b0 T
b0 "
b0 >
b0 W
b1000000010000000 6
b1000000010000000 Q
b10000100 7
b1000000001100111 $
b1000000001100111 P
b10000000 #
b10000000 O
b10000000 R
14
#540
04
#555
bx 6
bx Q
b0xxxxxxxxxxxxxxxxxxxx0 3
b0xxxxxxxxxxxxxxxxxxxx0 9
x1
b0xxxxxxxxxxxxxxxxxxxx0 *
b0xxxxxxxxxxxxxxxxxxxx0 N
bx !
bx =
bx I
bx X
bx "
bx >
bx W
bx %
bx ;
bx G
bx @
bx ?
bx A
bx M
bx V
bx U
bx T
b1000000010000100 5
b1000000010000100 S
b1000000010000000 2
b1000000010000000 8
b1000000010000100 7
bx $
bx P
b1000000010000000 #
b1000000010000000 O
b1000000010000000 R
14
#570
04
#585
bx 5
bx S
bx 7
bx #
bx O
bx R
14
